{
  "phonetic": "/iˈkweɪt/",
  "word_type": "verb",
  "definitions": [
    {
      "standard": "To consider synonymous or identical; to regard as equal."
    }
  ],
  "examples": [
    "Many people equate success with wealth.",
    "She would not let anyone else's opinion equate her belief in herself."
  ],
  "synonyms": [
    {
      "standard": "Associate",
      "phonetic": "/əˈsɜːʃn/",
      "examples": [
        "They associate exercise with good health.",
        "I often associated the scent of pine trees with Christmas."
      ]
    },
    {
      "standard": "Liken",
      "phonetic": "/ˈlaɪkin/",
      "examples": [
        "She likens her mother's advice to a guiding star.",
        "He likened his career path to that of an astronaut."
      ]
    }
  ],
  "antonyms": [
    {
      "standard": "Distinguish from; differentiate",
      "phonetic": "/dɪˈstɪŋkwɪʃnz frɒm/",
      "examples": [
        "The teacher asked the students to distinguish between facts and opinions.",
        "They learned how their personalities are distinguished by unique traits."
      ]
    }
  ]
}