{
  "phonetic": "/\\u0259b\\u02c8skj\\u0254\\u02d0(\\u0279)/;/\\u0259b\\u02c8skj\\u025d/",
  "word_type": "verb, adjective",
  "definitions": "To render obscure; to darken; to make dim; to keep in the dark; to hide; To conceal oneself; Difficult to understand.",
  "examples": "The speaker made obscure references to little-known literary works.;An etymological root of a word is unclear and open for debate.",
  "synonyms": "becloud, bedarken, bedim, bemist;cimmerian, dingy, fathomless, inscrutable, fuzzy, ill-defined, occluded, secluded, enigm0479123batic, esoteric",
  "antonyms": "clear"
}